LICENSE
MANIFEST.in
README.rst
requirements.txt
setup.cfg
setup.py
test-requirements.txt
ndic/__init__.py
ndic/constants.py
ndic/exceptions.py
ndic/search.py
ndic/utils.py
ndic.egg-info/PKG-INFO
ndic.egg-info/SOURCES.txt
ndic.egg-info/dependency_links.txt
ndic.egg-info/entry_points.txt
ndic.egg-info/requires.txt
ndic.egg-info/top_level.txt
ndic/scripts/__init__.py
ndic/scripts/search.py
ndic/tests/__init__.py
ndic/tests/test_search.py
ndic/tests/scripts/__init__.py
ndic/tests/scripts/test_search.py