Metadata-Version: 1.1
Name: ndic
Version: 1.8
Summary: Python module for NAVER English-Korean and Korean-English dictionaries
Home-page: https://github.com/jupiny/ndic
Author: jupiny
Author-email: tmdghks584@gmail.com
License: MIT
Download-URL: https://pypi.python.org/pypi/ndic
Platform: Posix; MacOS X; Windows
Classifier: Development Status :: 5 - Production/Stable
Classifier: Topic :: Software Development :: Testing
Classifier: Intended Audience :: Developers
Classifier: License :: OSI Approved :: MIT License
Classifier: Operating System :: OS Independent
Classifier: Programming Language :: Python
Classifier: Programming Language :: Python :: 2.6
Classifier: Programming Language :: Python :: 2.7
Classifier: Programming Language :: Python :: 3.3
Classifier: Programming Language :: Python :: 3.4
Classifier: Programming Language :: Python :: 3.5
Classifier: Programming Language :: Python :: Implementation :: PyPy
